{
  "MAINHAND": {
    "appliedenergistics2:certus_quartz_axe": 600,
    "appliedenergistics2:certus_quartz_sword": 856,
    "appliedenergistics2:nether_quartz_axe": 600,
    "appliedenergistics2:nether_quartz_sword": 856,
    "enderio:item_dark_steel_axe": 600,
    "enderio:item_dark_steel_bow": 850,
    "enderio:item_dark_steel_sword": 830,
    "enderio:item_end_steel_axe": 600,
    "enderio:item_end_steel_bow": 850,
    "enderio:item_end_steel_sword": 775,
    "energycontrol:nano_bow": 850,
    "extrautils2:compoundbow": 850,
    "extrautils2:fireaxe": 516,
    "extrautils2:lawsword": 600,
    "extrautils2:luxsaber": 711,
    "galacticraftcore:steel_sword": 856,
    "galacticraftplanets:desh_sword": 843,
    "galacticraftplanets:grapple": 850,
    "galacticraftplanets:titanium_sword": 744,
    "ic2:bronze_axe": 600,
    "ic2:bronze_sword": 856,
    "mekanismtools:bronzeaxe": 600,
    "mekanismtools:bronzesword": 744,
    "mekanismtools:glowstoneaxe": 600,
    "mekanismtools:glowstonesword": 775,
    "mekanismtools:lapislazuliaxe": 600,
    "mekanismtools:lapislazulisword": 856,
    "mekanismtools:obsidianaxe": 424,
    "mekanismtools:obsidiansword": 600,
    "mekanismtools:osmiumaxe": 600,
    "mekanismtools:osmiumsword": 804,
    "mekanismtools:steelaxe": 600,
    "mekanismtools:steelsword": 804,
    "minecraft:bow": 850,
    "minecraft:diamond_axe": 600,
    "minecraft:diamond_sword": 831,
    "minecraft:enchanted_book": 800,
    "minecraft:golden_axe": 676,
    "minecraft:golden_sword": 900,
    "minecraft:iron_axe": 600,
    "minecraft:iron_sword": 856,
    "minecraft:lingering_potion": 750,
    "minecraft:snowball": 900,
    "minecraft:splash_potion{Potion:\"minecraft:harming\"}": 750,
    "minecraft:stone_axe": 600,
    "minecraft:stone_sword": 879,
    "minecraft:tnt": 600,
    "minecraft:wooden_axe": 676,
    "minecraft:wooden_sword": 900,
    "projectred-exploration:athame": 900,
    "projectred-exploration:peridot_axe": 600,
    "projectred-exploration:peridot_sword": 837,
    "projectred-exploration:ruby_axe": 600,
    "projectred-exploration:ruby_sword": 831,
    "projectred-exploration:sapphire_axe": 600,
    "projectred-exploration:sapphire_sword": 831,
    "railcraft:tool_axe_steel": 600,
    "railcraft:tool_sword_steel": 843,
    "thermalfoundation:tool.bow_aluminum": 850,
    "thermalfoundation:tool.bow_bronze": 850,
    "thermalfoundation:tool.bow_constantan": 850,
    "thermalfoundation:tool.bow_copper": 850,
    "thermalfoundation:tool.bow_diamond": 850,
    "thermalfoundation:tool.bow_electrum": 850,
    "thermalfoundation:tool.bow_gold": 850,
    "thermalfoundation:tool.bow_invar": 850,
    "thermalfoundation:tool.bow_iron": 850,
    "thermalfoundation:tool.bow_lead": 850,
    "thermalfoundation:tool.bow_nickel": 850,
    "thermalfoundation:tool.bow_platinum": 850,
    "thermalfoundation:tool.bow_silver": 850,
    "thermalfoundation:tool.bow_steel": 850,
    "thermalfoundation:tool.bow_stone": 850,
    "thermalfoundation:tool.bow_tin": 850,
    "thermalfoundation:tool.sword_aluminum": 879,
    "thermalfoundation:tool.sword_bronze": 856,
    "thermalfoundation:tool.sword_constantan": 867,
    "thermalfoundation:tool.sword_copper": 879,
    "thermalfoundation:tool.sword_electrum": 889,
    "thermalfoundation:tool.sword_invar": 843,
    "thermalfoundation:tool.sword_lead": 879,
    "thermalfoundation:tool.sword_nickel": 843,
    "thermalfoundation:tool.sword_platinum": 817,
    "thermalfoundation:tool.sword_silver": 879,
    "thermalfoundation:tool.sword_steel": 843,
    "thermalfoundation:tool.sword_tin": 879,
    "twilightforest:ender_bow": 850,
    "twilightforest:fiery_sword": 804,
    "twilightforest:giant_sword": 879,
    "twilightforest:glass_sword": 1,
    "twilightforest:ice_bow": 850,
    "twilightforest:ice_sword": 817,
    "twilightforest:ironwood_axe": 600,
    "twilightforest:ironwood_sword": 856,
    "twilightforest:knightmetal_axe": 559,
    "twilightforest:knightmetal_sword": 831,
    "twilightforest:minotaur_axe": 559,
    "twilightforest:minotaur_axe_gold": 676,
    "twilightforest:seeker_bow": 850,
    "twilightforest:steeleaf_axe": 559,
    "twilightforest:steeleaf_sword": 831,
    "twilightforest:triple_bow": 850
  },
  "OFFHAND": {
    "enderio:item_dark_steel_shield": 850,
    "enderio:item_end_steel_shield": 850,
    "minecraft:ender_pearl": 600,
    "minecraft:flint_and_steel": 700,
    "minecraft:lava_bucket": 400,
    "minecraft:shield": 850,
    "twilightforest:knightmetal_shield": 850
  },
  "FEET": {
    "draconicevolution:draconic_boots": 891,
    "draconicevolution:wyvern_boots": 897,
    "enderio:item_dark_steel_boots": 554,
    "enderio:item_end_steel_boots": 349,
    "forestry:apiarist_boots": 907,
    "galacticraftcore:steel_boots": 599,
    "galacticraftplanets:desh_boots": 452,
    "galacticraftplanets:titanium_boots": 608,
    "ic2:bronze_boots": 778,
    "ic2:nano_boots": 605,
    "ic2:quantum_boots": 605,
    "ic2:rubber_boots": 691,
    "ic2:static_boots": 691,
    "mekanism:freerunners": 1000,
    "mekanismtools:bronzeboots": 556,
    "mekanismtools:glowstoneboots": 724,
    "mekanismtools:lapislazuliboots": 801,
    "mekanismtools:obsidianboots": 317,
    "mekanismtools:osmiumboots": 605,
    "mekanismtools:steelboots": 492,
    "minecraft:chainmail_boots": 844,
    "minecraft:diamond_boots": 683,
    "minecraft:golden_boots": 900,
    "minecraft:iron_boots": 839,
    "minecraft:leather_boots": 932,
    "opencomputers:hoverboots": 596,
    "projectred-exploration:peridot_boots": 768,
    "projectred-exploration:ruby_boots": 750,
    "projectred-exploration:sapphire_boots": 750,
    "railcraft:armor_boots_steel": 670,
    "tconstruct:slime_boots": 1000,
    "thermalfoundation:armor.boots_aluminum": 822,
    "thermalfoundation:armor.boots_bronze": 741,
    "thermalfoundation:armor.boots_constantan": 807,
    "thermalfoundation:armor.boots_copper": 857,
    "thermalfoundation:armor.boots_electrum": 843,
    "thermalfoundation:armor.boots_invar": 707,
    "thermalfoundation:armor.boots_lead": 814,
    "thermalfoundation:armor.boots_nickel": 773,
    "thermalfoundation:armor.boots_platinum": 537,
    "thermalfoundation:armor.boots_silver": 852,
    "thermalfoundation:armor.boots_steel": 698,
    "thermalfoundation:armor.boots_tin": 874,
    "twilightforest:arctic_boots": 830,
    "twilightforest:fiery_boots": 639,
    "twilightforest:ironwood_boots": 715,
    "twilightforest:knightmetal_boots": 708,
    "twilightforest:steeleaf_boots": 816,
    "twilightforest:yeti_boots": 702
  },
  "LEGS": {
    "draconicevolution:draconic_legs": 891,
    "draconicevolution:wyvern_legs": 897,
    "enderio:item_dark_steel_leggings": 554,
    "enderio:item_end_steel_leggings": 349,
    "forestry:apiarist_legs": 907,
    "galacticraftcore:steel_leggings": 599,
    "galacticraftplanets:desh_leggings": 452,
    "galacticraftplanets:titanium_leggings": 608,
    "ic2:bronze_leggings": 778,
    "ic2:hazmat_leggings": 691,
    "ic2:nano_leggings": 605,
    "ic2:quantum_leggings": 605,
    "mekanismtools:bronzeleggings": 556,
    "mekanismtools:glowstoneleggings": 724,
    "mekanismtools:lapislazulileggings": 801,
    "mekanismtools:obsidianleggings": 317,
    "mekanismtools:osmiumleggings": 605,
    "mekanismtools:steelleggings": 492,
    "minecraft:chainmail_leggings": 844,
    "minecraft:diamond_leggings": 683,
    "minecraft:golden_leggings": 900,
    "minecraft:iron_leggings": 839,
    "minecraft:leather_leggings": 932,
    "projectred-exploration:peridot_leggings": 768,
    "projectred-exploration:ruby_leggings": 750,
    "projectred-exploration:sapphire_leggings": 750,
    "railcraft:armor_leggings_steel": 670,
    "railcraft:armor_overalls": 907,
    "thermalfoundation:armor.legs_aluminum": 822,
    "thermalfoundation:armor.legs_bronze": 741,
    "thermalfoundation:armor.legs_constantan": 807,
    "thermalfoundation:armor.legs_copper": 857,
    "thermalfoundation:armor.legs_electrum": 843,
    "thermalfoundation:armor.legs_invar": 707,
    "thermalfoundation:armor.legs_lead": 814,
    "thermalfoundation:armor.legs_nickel": 773,
    "thermalfoundation:armor.legs_platinum": 537,
    "thermalfoundation:armor.legs_silver": 852,
    "thermalfoundation:armor.legs_steel": 698,
    "thermalfoundation:armor.legs_tin": 874,
    "twilightforest:arctic_leggings": 830,
    "twilightforest:fiery_leggings": 639,
    "twilightforest:ironwood_leggings": 715,
    "twilightforest:knightmetal_leggings": 708,
    "twilightforest:naga_leggings": 697,
    "twilightforest:steeleaf_leggings": 816,
    "twilightforest:yeti_leggings": 702
  },
  "CHEST": {
    "draconicevolution:draconic_chest": 891,
    "draconicevolution:wyvern_chest": 897,
    "enderio:item_dark_steel_chestplate": 554,
    "enderio:item_end_steel_chestplate": 349,
    "forestry:apiarist_chest": 907,
    "galacticraftcore:steel_chestplate": 599,
    "galacticraftplanets:desh_chestplate": 452,
    "galacticraftplanets:titanium_chestplate": 608,
    "ic2:advanced_batpack": 605,
    "ic2:alloy_chestplate": 365,
    "ic2:batpack": 605,
    "ic2:bronze_chestplate": 778,
    "ic2:cf_pack": 691,
    "ic2:energy_pack": 605,
    "ic2:hazmat_chestplate": 691,
    "ic2:jetpack": 691,
    "ic2:jetpack_electric": 605,
    "ic2:lappack": 605,
    "ic2:nano_chestplate": 605,
    "ic2:quantum_chestplate": 605,
    "mekanism:armoredjetpack": 1000,
    "mekanism:jetpack": 1000,
    "mekanism:scubatank": 1000,
    "mekanismtools:bronzechestplate": 556,
    "mekanismtools:glowstonechestplate": 724,
    "mekanismtools:lapislazulichestplate": 801,
    "mekanismtools:obsidianchestplate": 317,
    "mekanismtools:osmiumchestplate": 605,
    "mekanismtools:steelchestplate": 492,
    "minecraft:chainmail_chestplate": 844,
    "minecraft:diamond_chestplate": 683,
    "minecraft:golden_chestplate": 900,
    "minecraft:iron_chestplate": 839,
    "minecraft:leather_chestplate": 932,
    "openblocks:crane_backpack": 839,
    "openblocks:sleeping_bag": 839,
    "projectred-expansion:jetpack": 596,
    "projectred-exploration:peridot_chestplate": 768,
    "projectred-exploration:ruby_chestplate": 750,
    "projectred-exploration:sapphire_chestplate": 750,
    "railcraft:armor_chestplate_steel": 670,
    "tconstruct:piggybackpack": 1000,
    "thermalfoundation:armor.plate_aluminum": 822,
    "thermalfoundation:armor.plate_bronze": 741,
    "thermalfoundation:armor.plate_constantan": 807,
    "thermalfoundation:armor.plate_copper": 857,
    "thermalfoundation:armor.plate_electrum": 843,
    "thermalfoundation:armor.plate_invar": 707,
    "thermalfoundation:armor.plate_lead": 814,
    "thermalfoundation:armor.plate_nickel": 773,
    "thermalfoundation:armor.plate_platinum": 537,
    "thermalfoundation:armor.plate_silver": 852,
    "thermalfoundation:armor.plate_steel": 698,
    "thermalfoundation:armor.plate_tin": 874,
    "twilightforest:arctic_chestplate": 830,
    "twilightforest:fiery_chestplate": 639,
    "twilightforest:ironwood_chestplate": 715,
    "twilightforest:knightmetal_chestplate": 708,
    "twilightforest:naga_chestplate": 697,
    "twilightforest:phantom_chestplate": 600,
    "twilightforest:steeleaf_chestplate": 816,
    "twilightforest:yeti_chestplate": 702
  },
  "HEAD": {
    "draconicevolution:draconic_helm": 891,
    "draconicevolution:wyvern_helm": 897,
    "enderio:item_dark_steel_helmet": 554,
    "enderio:item_end_steel_helmet": 349,
    "forestry:apiarist_helmet": 907,
    "forestry:naturalist_helmet": 932,
    "galacticraftcore:sensor_glasses": 1,
    "galacticraftcore:steel_helmet": 599,
    "galacticraftplanets:desh_helmet": 452,
    "galacticraftplanets:titanium_helmet": 608,
    "ic2:bronze_helmet": 778,
    "ic2:hazmat_helmet": 691,
    "ic2:nano_helmet": 605,
    "ic2:nightvision_goggles": 605,
    "ic2:quantum_helmet": 605,
    "ic2:solar_helmet": 605,
    "mekanism:gasmask": 1000,
    "mekanismtools:bronzehelmet": 556,
    "mekanismtools:glowstonehelmet": 724,
    "mekanismtools:lapislazulihelmet": 801,
    "mekanismtools:obsidianhelmet": 317,
    "mekanismtools:osmiumhelmet": 605,
    "mekanismtools:steelhelmet": 492,
    "minecraft:chainmail_helmet": 844,
    "minecraft:diamond_helmet": 683,
    "minecraft:golden_helmet": 900,
    "minecraft:iron_helmet": 839,
    "minecraft:leather_helmet": 932,
    "openblocks:crayon_glasses": 900,
    "openblocks:pencil_glasses": 900,
    "openblocks:serious_glasses": 900,
    "openblocks:sonic_glasses": 839,
    "openblocks:technicolor_glasses": 900,
    "projectred-exploration:peridot_helmet": 768,
    "projectred-exploration:ruby_helmet": 750,
    "projectred-exploration:sapphire_helmet": 750,
    "quark:witch_hat": 922,
    "railcraft:armor_goggles": 744,
    "railcraft:armor_helmet_steel": 670,
    "thermalfoundation:armor.helmet_aluminum": 822,
    "thermalfoundation:armor.helmet_bronze": 741,
    "thermalfoundation:armor.helmet_constantan": 807,
    "thermalfoundation:armor.helmet_copper": 857,
    "thermalfoundation:armor.helmet_electrum": 843,
    "thermalfoundation:armor.helmet_invar": 707,
    "thermalfoundation:armor.helmet_lead": 814,
    "thermalfoundation:armor.helmet_nickel": 773,
    "thermalfoundation:armor.helmet_platinum": 537,
    "thermalfoundation:armor.helmet_silver": 852,
    "thermalfoundation:armor.helmet_steel": 698,
    "thermalfoundation:armor.helmet_tin": 874,
    "twilightforest:arctic_helmet": 830,
    "twilightforest:fiery_helmet": 639,
    "twilightforest:ironwood_helmet": 715,
    "twilightforest:knightmetal_helmet": 708,
    "twilightforest:phantom_helmet": 600,
    "twilightforest:steeleaf_helmet": 816,
    "twilightforest:yeti_helmet": 702
  }
}